raypyng/__init__.py
raypyng/beamwaist.py
raypyng/collections.py
raypyng/config.py
raypyng/diodes.py
raypyng/dipole_flux.py
raypyng/errors.py
raypyng/helper_functions.py
raypyng/postprocessing.py
raypyng/recipes.py
raypyng/rml.py
raypyng/runner.py
raypyng/simulate.py
raypyng/vls_grating.py
raypyng/wave_helper.py
raypyng/diodes_data/AXUV.py
raypyng/diodes_data/GaAsP.py
raypyng/diodes_data/__init__.py
raypyng/diodes_data/convert.py
raypyng/xmltools/__init__.py
raypyng/xmltools/attributes.py
raypyng/xmltools/dictionaries.py
raypyng/xmltools/elements.py
raypyng/xmltools/parser.py
raypyng-1.3.53.dist-info/licenses/LICENSE
raypyng-1.3.53.dist-info/METADATA
raypyng-1.3.53.dist-info/WHEEL
raypyng-1.3.53.dist-info/top_level.txt
raypyng-1.3.53.dist-info/RECORD
