Metadata-Version: 2.4
Name: raypyng
Version: 1.3.53
Summary: Python interface for RAY-UI x-ray tracing program
Author-email: "Simone Vadilonga, Ruslan Ovsyannikov, Sebastian Sachse" <simone.vadilonga@helmholtz-berlin.de>
License: The MIT License (MIT)
Classifier: Programming Language :: Python :: 3
Classifier: License :: OSI Approved :: MIT License
Requires-Python: >=3.10
License-File: LICENSE
Requires-Dist: numpy>=1.22.0
Requires-Dist: psutil>=5.9.1
Requires-Dist: joblib>=1.1.0
Requires-Dist: matplotlib>=3.5.1
Requires-Dist: natsort>=8.2.0
Requires-Dist: tqdm>=4.66.1
Requires-Dist: pandas>=2.0.3
Requires-Dist: srxraylib>=1.0.61
Dynamic: license-file
